bas_style_kit_jinja_templates/__init__.py
bas_style_kit_jinja_templates/templates/includes/body--analytics-script.j2
bas_style_kit_jinja_templates/templates/includes/body--back-to-top.j2
bas_style_kit_jinja_templates/templates/includes/body--core-scripts.j2
bas_style_kit_jinja_templates/templates/includes/bsk--body--standard-header.j2
bas_style_kit_jinja_templates/templates/includes/bsk--footer--back-to-top.j2
bas_style_kit_jinja_templates/templates/includes/bsk--footer--governance.j2
bas_style_kit_jinja_templates/templates/includes/bsk--footer--is-something-wrong.j2
bas_style_kit_jinja_templates/templates/includes/bsk--footer--policy-links.j2
bas_style_kit_jinja_templates/templates/includes/bsk--head--favicon.j2
bas_style_kit_jinja_templates/templates/includes/bsk--header--cookie-notice.j2
bas_style_kit_jinja_templates/templates/includes/bsk--header--site-development-phase.j2
bas_style_kit_jinja_templates/templates/includes/bsk--header--site-navigation.j2
bas_style_kit_jinja_templates/templates/includes/head--core-metadata.j2
bas_style_kit_jinja_templates/templates/includes/head--core-styles.j2
bas_style_kit_jinja_templates/templates/includes/head--seo-metadata.j2
bas_style_kit_jinja_templates/templates/layouts/blank.j2
bas_style_kit_jinja_templates/templates/layouts/bsk_base.j2
bas_style_kit_jinja_templates/templates/layouts/bsk_standard.j2
bas_style_kit_jinja_templates/templates/layouts/html.j2
bas_style_kit_jinja_templates/templates/macros/bsk--nav.j2
bas_style_kit_jinja_templates/templates/macros/bsk_pattern_item_type_header.j2
bas_style_kit_jinja_templates/templates/macros/bsk_pattern_orcid_id.j2
bas_style_kit_jinja_templates/templates/patterns/bsk_page-not-found.j2
bas_style_kit_jinja_templates/templates/patterns/bsk_problem-with-service.j2
bas_style_kit_jinja_templates/templates/patterns/bsk_service-unavailable.j2
bas_style_kit_jinja_templates/templates/patterns/bsk_sign-in-microsoft.j2
bas_style_kit_jinja_templates/templates/patterns/bsk_start.j2
bas_style_kit_jinja_templates-0.7.1.dist-info/LICENSE.md
bas_style_kit_jinja_templates-0.7.1.dist-info/METADATA
bas_style_kit_jinja_templates-0.7.1.dist-info/WHEEL
bas_style_kit_jinja_templates-0.7.1.dist-info/RECORD
