Metadata-Version: 2.1
Name: bas-style-kit-jinja-templates
Version: 0.7.1
Summary: A set of Jinja2 templates implementing the BAS Style Kit
Home-page: https://github.com/antarctica/bas-style-kit-jinja-templates
License: MIT
Author: Felix Fennell
Author-email: felnne@bas.ac.uk
Requires-Python: >=3.6,<4.0
Classifier: Development Status :: 5 - Production/Stable
Classifier: Intended Audience :: Developers
Classifier: License :: OSI Approved :: MIT License
Classifier: License :: Other/Proprietary License
Classifier: Operating System :: OS Independent
Classifier: Programming Language :: Python :: 3
Classifier: Programming Language :: Python :: 3.6
Classifier: Programming Language :: Python :: 3.7
Classifier: Programming Language :: Python :: 3.8
Classifier: Programming Language :: Python :: 3.9
Classifier: Programming Language :: Python :: 3.10
Classifier: Programming Language :: Python :: 3.11
Classifier: Programming Language :: Python :: 3.12
Requires-Dist: Jinja2 (>=3.0.3,<4.0.0)
Project-URL: Repository, https://github.com/antarctica/bas-style-kit-jinja-templates
